<?xml version="1.0" encoding="UTF-8"?>
<parallel xmlns:xsi="http://www.w3.org/2001/XMLSchema-instance" xsi:noNamespaceSchemaLocation="../../HNTAshaninka/ParallelCorpus/parallel_texts.xsd">
    <text id="1">
        <sentence lang="es">DIOS WAWANKUNAMAN RIMAN</sentence>
        <sentence lang="quz">DIOS HABLA A SUS HIJOS</sentence>
        <morphology>


DIOS	dios[NRootES]

WAWANKUNAMAN	wawa[NRoot][=niño][^DB][--]n[NPers][+3.Poss][--]kuna[Num][+Pl][^DB][--]man[Cas][+Dat_Ill]

RIMAN	rima[VRoot][=hablar][^DB][--]n[VPers][+3.Sg.Subj]

</morphology>
        <parsing>
            


</parsing>
    </text>
    <text id="2">
        <sentence lang="es">DE LOS LIBROS DEL ANTIGUO TESTAMENTO</sentence>
        <sentence lang="quz">ÑAWPA TESTAMENTO QELQAKUNAMANTA</sentence>
        <morphology>


ÑAWPA	ñawpa[NRoot][=antes]

TESTAMENTO	testamento[NRootES]

QELQAKUNAMANTA	qillqa[NRoot][=letra][--]kuna[Num][+Pl][^DB][--]manta[Cas][+Abl]

</morphology>
        <parsing/>
    </text>
    <text id="0003">
        <sentence lang="es">LOS ORÍGENES</sentence>
        <sentence lang="quz">QALLARIYKUNA</sentence>
        <morphology>


QALLARIYKUNA	qalla[VRoot][=empezar][--]ri[VDeriv][+Inch][^DB][--]y[NS][+Inf][--]kuna[Num][+Pl]

</morphology>
        <parsing/>
    </text>
    <text id="4">
        <sentence lang="es">1. Dios crea el mundo</sentence>
        <sentence lang="quz">1. Dios teqsimuyuta kaman</sentence>
        <morphology>


Dios	dios[NRootES]

teqsimuyuta	tiqsimuyu[NRoot][=globo,tierra,mundo][^DB][--]ta[Cas][+Acc]

kaman	kama[VRoot][=gobernar,mandar,crear][^DB][--]n[VPers][+3.Sg.Subj]

</morphology>
        <parsing/>
    </text>
    <text id="5">
        <sentence lang="es">Al principio creó Dios el cielo y la tierra.</sentence>
        <sentence lang="quz">Ñawpaqtaqa Dios kamarqan hanaqpachata teqsimuyuta ima.</sentence>
        <morphology>


Ñawpaqtaqa	ñawpaq[NRoot][=antes][^DB][--]ta[Cas][+Acc][^DB][--]qa[Amb][+Top]

Dios	dios[NRootES]

kamarqan	kama[VRoot][=gobernar,mandar,crear][^DB][--]rqa[Tns][+NPst][--]n[VPers][+3.Sg.Subj]

hanaqpachata	hanaq[NRoot][=arriba,superior][^DB][--]pacha[NRoot][=tiempo,mundo][^DB][--]ta[Cas][+Acc]

teqsimuyuta	tiqsimuyu[NRoot][=globo,tierra,mundo][^DB][--]ta[Cas][+Acc]

ima	ima[Part_Conec]

.	.[$.]

</morphology>
        <parsing/>
    </text>
    <text id="6">
        <sentence lang="es">La tierra estaba desierta y vacía.</sentence>
        <sentence lang="quz">Kay pachan ch’inneqtaq ch’usaqtaq ima kasharqan.</sentence>
        <morphology>


Kay	kay[PrnDem]

pachan	pacha[NRoot][=mundo,tiempo][^DB][--]m[Amb][+DirE]

ch'inneqtaq	ch'inni[VRoot][=callar,apagarse][^DB][--]q[NS][+Ag][^DB][--]taq[Amb][+Con_Intr]

ch'usaqtaq	ch'usaq[NRoot][=nada,vacío,ausente][^DB][--]taq[Amb][+Con_Intr]

ima	ima[Part_Conec]

kasharqan	ka[VRoot][=ser][^DB][--]chka[Asp][+Prog][--]rqa[Tns][+NPst][--]n[VPers][+3.Sg.Subj]

.	.[$.]

</morphology>
        <parsing/>
    </text>
    <text id="7">
        <sentence lang="es">Pero el Espíritu de Dios se movía sobre las aguas.</sentence>
        <sentence lang="quz">Ichaqa Diospa espiritunmi unuq patanpi kuyukachasharqan.</sentence>
        <sentence lang="qu">Ichaqa Diospa espíritunmi unup patanpi kuyukachachkarqan.</sentence>
        <morphology>


Ichaqa	icha[Part_Contr][^DB][--]qa[Amb][+Top]

Diospa	dios[NRootES][^DB][--]pa[Cas][+Gen]

espiritunmi	espíritu[NRootES][^DB][--]n[NPers][+3.Sg.Poss][^DB][--]mi[Amb][+DirE]

unuq	unu[NRoot][=agua,millón][^DB][--]p[Cas][+Gen]

patanpi	pata[NRoot][=al_lado,arriba][^DB][--]n[NPers][+3.Sg.Poss][^DB][--]pi[Cas][+Loc]

.	.[$.]

</morphology>
        <parsing/>
    </text>
    <text id="8">
        <sentence lang="es">Entonces dijo Dios: -Que exista la luz. Y la luz dio claridad.</sentence>
        <sentence lang="quz">Chhaynaqa, Dios nirqan: -K’anchay kachun, nispa. Hinan, k’anchay kapurqan.</sentence>
        <morphology/>
        <parsing/>
    </text>
    <text id="9">
        <sentence lang="es">Dios vio que la luz era buena.</sentence>
        <sentence lang="quz">Dios, k’anchay allin kasqanta rikurqan.</sentence>
        <morphology format="" analysislevel=""/>
        <parsing format="" analysislevel=""/>
    </text>
    <text id="10">
        <sentence lang="es">Dios separó la luz de la oscuridad.</sentence>
        <sentence lang="quz">Dios, k’anchayta laqhamanta t’aqarqan.</sentence>
        <morphology format="" analysislevel=""/>
        <parsing format="" analysislevel=""/>
    </text>
    <text id="11">
        <sentence lang="es">Dijo a la luz: -Tú eres el día.</sentence>
        <sentence lang="quz">Dios, k’anchayta nirqan: -Qanmi p’unchaw kanki, nispa.</sentence>
        <morphology format="" analysislevel=""/>
        <parsing format="" analysislevel=""/>
    </text>
</parallel>
